Log4j2ZhongwenWendang/README.md
Log4j2ZhongwenWendang/__init__.py
Log4j2ZhongwenWendang/__main__.py
Log4j2ZhongwenWendang/file.epub
Log4j2ZhongwenWendang/index.html
Log4j2ZhongwenWendang/css/__init__.py
Log4j2ZhongwenWendang/css/annotations.css
Log4j2ZhongwenWendang/css/main.css
Log4j2ZhongwenWendang/css/normalize.css
Log4j2ZhongwenWendang/css/popup.css
Log4j2ZhongwenWendang/font/__init__.py
Log4j2ZhongwenWendang/font/fontello.eot
Log4j2ZhongwenWendang/font/fontello.svg
Log4j2ZhongwenWendang/font/fontello.ttf
Log4j2ZhongwenWendang/font/fontello.woff
Log4j2ZhongwenWendang/img/__init__.py
Log4j2ZhongwenWendang/img/annotator-glyph-sprite.png
Log4j2ZhongwenWendang/img/annotator-icon-sprite.png
Log4j2ZhongwenWendang/img/apple-touch-icon.png
Log4j2ZhongwenWendang/img/cancelfullscreen.png
Log4j2ZhongwenWendang/img/close.png
Log4j2ZhongwenWendang/img/fullscreen.png
Log4j2ZhongwenWendang/img/loader.gif
Log4j2ZhongwenWendang/img/menu-icon.png
Log4j2ZhongwenWendang/img/save.png
Log4j2ZhongwenWendang/img/saved.png
Log4j2ZhongwenWendang/img/settings-s.png
Log4j2ZhongwenWendang/img/settings.png
Log4j2ZhongwenWendang/img/star.png
Log4j2ZhongwenWendang/js/__init__.py
Log4j2ZhongwenWendang/js/epub.js
Log4j2ZhongwenWendang/js/epub.min.js
Log4j2ZhongwenWendang/js/epub.min.map
Log4j2ZhongwenWendang/js/hooks.min.js
Log4j2ZhongwenWendang/js/hooks.min.map
Log4j2ZhongwenWendang/js/reader.js
Log4j2ZhongwenWendang/js/reader.js.map
Log4j2ZhongwenWendang/js/reader.min.js
Log4j2ZhongwenWendang/js/reader.min.map
Log4j2ZhongwenWendang/js/hooks/__init__.py
Log4j2ZhongwenWendang/js/hooks/extensions/__init__.py
Log4j2ZhongwenWendang/js/hooks/extensions/highlight.js
Log4j2ZhongwenWendang/js/libs/__init__.py
Log4j2ZhongwenWendang/js/libs/jquery.min.js
Log4j2ZhongwenWendang/js/libs/localforage.min.js
Log4j2ZhongwenWendang/js/libs/screenfull.js
Log4j2ZhongwenWendang/js/libs/screenfull.min.js
Log4j2ZhongwenWendang/js/libs/zip.min.js
Log4j2ZhongwenWendang/js/plugins/__init__.py
log4j2_zhongwen_wendang-2024.3.5.0.dist-info/METADATA
log4j2_zhongwen_wendang-2024.3.5.0.dist-info/WHEEL
log4j2_zhongwen_wendang-2024.3.5.0.dist-info/entry_points.txt
log4j2_zhongwen_wendang-2024.3.5.0.dist-info/top_level.txt
log4j2_zhongwen_wendang-2024.3.5.0.dist-info/RECORD
